rusocsci/__init__.py
rusocsci/buttonbox.py
rusocsci/extended.py
rusocsci/joystick.py
rusocsci/utils.py
RuSocSci-0.9.2.dist-info/LICENSE
RuSocSci-0.9.2.dist-info/METADATA
RuSocSci-0.9.2.dist-info/WHEEL
RuSocSci-0.9.2.dist-info/top_level.txt
RuSocSci-0.9.2.dist-info/RECORD
