Metadata-Version: 2.1
Name: RuSocSci
Version: 0.9.2
Summary: Support package for Radboud University Nijmegen, Faculty of Social Sciences hardware, with PsychoPy-like API.
Home-page: https://www.socsci.ru.nl/wilberth/python/rusocsci.html
Author: Wilbert van Ham
Author-email: w.vanham@socsci.ru.nl
License: GPLv3+
Keywords: hardware
Platform: UNKNOWN
Classifier: Development Status :: 4 - Beta
Classifier: License :: OSI Approved :: GNU General Public License v3 or later (GPLv3+)
Requires-Python: >=2.6
License-File: LICENSE
Requires-Dist: pyserial
